hwb/__init__.py
hwb/blots.py
hwb/configs.py
hwb/utils.py
tests/__init__.py
tests/conftest.py
tests/test_hand_written_blot.py
tests/test_utils.py
hwb-0.0.15.dist-info/LICENSE
hwb-0.0.15.dist-info/METADATA
hwb-0.0.15.dist-info/WHEEL
hwb-0.0.15.dist-info/top_level.txt
hwb-0.0.15.dist-info/RECORD
