Metadata-Version: 2.1
Name: hwb
Version: 0.0.15
Summary: Hand written blot augmentation.
Home-page: https://github.com/TheDenk/hwb
Author: Karachev Denis
Author-email: welcomedenk@gmail.com
License: MIT
Platform: UNKNOWN
Requires-Dist: bezier
Requires-Dist: opencv-python (>=4.1.1)
